COPYING
COPYING.LESSER
MANIFEST.in
README.rst
package.py
requirements.txt
setup.py
version
Mocki.egg-info/PKG-INFO
Mocki.egg-info/SOURCES.txt
Mocki.egg-info/dependency_links.txt
Mocki.egg-info/requires.txt
Mocki.egg-info/top_level.txt
mocki/__init__.py
mocki/actions.py
mocki/core.py
mocki/expectations.py
mocki/matchers.py