Metadata-Version: 1.0
Name: Mocki
Version: 1.7.5
Summary: An easy-to-use but full featured mocking library for Python.
Home-page: https://bitbucket.org/okozak/mocki
Author: Olivier Kozak
Author-email: olivier.kozak@gmail.com
License: GNU LGPL v3
Platform: UNKNOWN
